setup.py
i3barfodder/__init__.py
i3barfodder/config.py
i3barfodder/constants.py
i3barfodder/error.py
i3barfodder/i3barproto.py
i3barfodder/main.py
i3barfodder/profile.py
i3barfodder/util.py
i3barfodder/validation.py
i3barfodder/widgets.py
i3barfodder/worker.py
i3barfodder.egg-info/PKG-INFO
i3barfodder.egg-info/SOURCES.txt
i3barfodder.egg-info/dependency_links.txt
i3barfodder.egg-info/entry_points.txt
i3barfodder.egg-info/requires.txt
i3barfodder.egg-info/top_level.txt
i3bfutils/__init__.py
i3bfutils/cache.py
i3bfutils/convert.py
i3bfutils/cpu.py
i3bfutils/dates.py
i3bfutils/delay.py
i3bfutils/inotify.py
i3bfutils/io.py
i3bfutils/mail.py
i3bfutils/network.py
i3bfutils/pkgmgr.py
i3bfutils/rate.py
i3bfutils/sensors.py
i3bfutils/storage.py
i3bfutils/template.py
workers/i3bf-cpu
workers/i3bf-mail
workers/i3bf-net
workers/i3bf-pkgmgr
workers/i3bf-storage
workers/i3bf-temperature
workers/i3bf-timedate