Metadata-Version: 1.1
Name: i3barfodder
Version: 0.3.0
Summary: Powerful i3bar status line generator
Home-page: https://gitlab.com/rndusr/i3barfodder
Author: Random User
Author-email: rndusr@posteo.de
License: GPLv3+
Keywords: i3 i3bar
Platform: UNKNOWN
Classifier: License :: OSI Approved :: GNU General Public License v3 or later (GPLv3+)
Classifier: Topic :: System :: Monitoring
Classifier: Programming Language :: Python :: 3.4
